octogen/api/__init__.py
octogen/api/_base_client.py
octogen/api/_client.py
octogen/api/_compat.py
octogen/api/_constants.py
octogen/api/_exceptions.py
octogen/api/_files.py
octogen/api/_models.py
octogen/api/_qs.py
octogen/api/_resource.py
octogen/api/_response.py
octogen/api/_streaming.py
octogen/api/_types.py
octogen/api/_version.py
octogen/api/py.typed
octogen/api/_utils/__init__.py
octogen/api/_utils/_logs.py
octogen/api/_utils/_proxy.py
octogen/api/_utils/_reflection.py
octogen/api/_utils/_resources_proxy.py
octogen/api/_utils/_streams.py
octogen/api/_utils/_sync.py
octogen/api/_utils/_transform.py
octogen/api/_utils/_typing.py
octogen/api/_utils/_utils.py
octogen/api/lib/.keep
octogen/api/resources/__init__.py
octogen/api/resources/catalog.py
octogen/api/types/__init__.py
octogen/api/types/aggregate_offer.py
octogen/api/types/audience.py
octogen/api/types/brand.py
octogen/api/types/breadcrumb_list.py
octogen/api/types/catalog_agent_search_params.py
octogen/api/types/catalog_style_and_tags_search_params.py
octogen/api/types/catalog_text_search_params.py
octogen/api/types/catalog_upload_file_params.py
octogen/api/types/catalog_upload_file_response.py
octogen/api/types/category.py
octogen/api/types/color_info.py
octogen/api/types/context_enum.py
octogen/api/types/facet_param.py
octogen/api/types/fulfillment_info.py
octogen/api/types/image.py
octogen/api/types/offer.py
octogen/api/types/offers.py
octogen/api/types/organization.py
octogen/api/types/product_enrichment.py
octogen/api/types/promotion.py
octogen/api/types/quantitative_value.py
octogen/api/types/rating.py
octogen/api/types/review.py
octogen/api/types/search_tool_output.py
octogen/api/types/three_d_model.py
octogen/api/types/video_object.py
octogen_api-0.1.0a9.dist-info/METADATA
octogen_api-0.1.0a9.dist-info/WHEEL
octogen_api-0.1.0a9.dist-info/licenses/LICENSE
octogen_api-0.1.0a9.dist-info/RECORD
